//@class:dxc/junit/opcodes/jsr_w/jm/T_jsr_w_5
// parsed:, offset 0, len 0, h: begin classfile
// parsed:, offset 0, len 4, h: magic: cafebabe
// .  .  .  .  
   ca fe ba be 
// parsed:, offset 4, len 2, h: minor_version: 0003
// .  .  
   00 03 
// parsed:, offset 6, len 2, h: major_version: 002d
// .  -  
   00 2d 
// parsed:, offset 8, len 2, h: constant_pool_count: 0012
// .  .  
   00 12 
// parsed:, offset 10, len 0, h:  constant_pool:
    // parsed:, offset 10, len 5, h: 0001: method{java.lang.Object.<init>:()V}
    // .  .  .  .  .  
       0a 00 0e 00 08 
    // parsed:, offset 15, len 19, h: 0002: utf8{"java/lang/Object"}
    // .  .  .  j  a  v  a  /  l  a  n  g  /  O  b  j  e  c  t  
       01 00 10 6a 61 76 61 2f 6c 61 6e 67 2f 4f 62 6a 65 63 74 
    // parsed:, offset 34, len 13, h: 0003: utf8{"SourceFile"}
    // .  .  .  S  o  u  r  c  e  F  i  l  e  
       01 00 0a 53 6f 75 72 63 65 46 69 6c 65 
    // parsed:, offset 47, len 3, h: 0004: type{dxc.junit.opcodes.jsr_w.jm.T_jsr_w_5}
    // .  .  .  
       07 00 07 
    // parsed:, offset 50, len 9, h: 0005: utf8{"<init>"}
    // .  .  .  <  i  n  i  t  >  
       01 00 06 3c 69 6e 69 74 3e 
    // parsed:, offset 59, len 6, h: 0006: utf8{"run"}
    // .  .  .  r  u  n  
       01 00 03 72 75 6e 
    // parsed:, offset 65, len 39, h: 0007: utf8{"dxc/junit/opcodes/jsr_w/jm/T_jsr_w_5"}
    // .  .  $  d  x  c  /  j  u  n  i  t  /  o  p  c  o  d  e  s  /  j  s  r  _  w  /  j  m  /  T  _  j  s  r  _  w  _  5  
       01 00 24 64 78 63 2f 6a 75 6e 69 74 2f 6f 70 63 6f 64 65 73 2f 6a 73 72 5f 77 2f 6a 6d 2f 54 5f 6a 73 72 5f 77 5f 35 
    // parsed:, offset 104, len 5, h: 0008: nat{<init>:()V}
    // .  .  .  .  .  
       0c 00 05 00 0c 
    // parsed:, offset 109, len 5, h: 0009: utf8{"i1"}
    // .  .  .  i  1  
       01 00 02 69 31 
    // parsed:, offset 114, len 7, h: 000a: utf8{"Code"}
    // .  .  .  C  o  d  e  
       01 00 04 43 6f 64 65 
    // parsed:, offset 121, len 6, h: 000b: utf8{"()Z"}
    // .  .  .  (  )  Z  
       01 00 03 28 29 5a 
    // parsed:, offset 127, len 6, h: 000c: utf8{"()V"}
    // .  .  .  (  )  V  
       01 00 03 28 29 56 
    // parsed:, offset 133, len 5, h: 000d: field{dxc.junit.opcodes.jsr_w.jm.T_jsr_w_5.i1:I}
    // .  .  .  .  .  
       09 00 04 00 11 
    // parsed:, offset 138, len 3, h: 000e: type{java.lang.Object}
    // .  .  .  
       07 00 02 
    // parsed:, offset 141, len 4, h: 000f: utf8{"I"}
    // .  .  .  I  
       01 00 01 49 
    // parsed:, offset 145, len 17, h: 0010: utf8{"T_jsr_w_5.java"}
    // .  .  .  T  _  j  s  r  _  w  _  5  .  j  a  v  a  
       01 00 0e 54 5f 6a 73 72 5f 77 5f 35 2e 6a 61 76 61 
    // parsed:, offset 162, len 5, h: 0011: nat{i1:I}
    // .  .  .  .  .  
       0c 00 09 00 0f 
// parsed:, offset 167, len 0, h: end constant_pool
// parsed:, offset 167, len 2, h: access_flags: public|super
// .  !  
   00 21 
// parsed:, offset 169, len 2, h: this_class: type{dxc.junit.opcodes.jsr_w.jm.T_jsr_w_5}
// .  .  
   00 04 
// parsed:, offset 171, len 2, h: super_class: type{java.lang.Object}
// .  .  
   00 0e 
// parsed:, offset 173, len 2, h: interfaces_count: 0000
// .  .  
   00 00 
// parsed:, offset 175, len 2, h: fields_count: 0001
// .  .  
   00 01 
// ========== start-ParseMember:i1, offset 177, len:106,desc: I
// parsed:, offset 177, len 0, h:  fields[0]: 
    // parsed:, offset 177, len 2, h: access_flags: public
    // .  .  
       00 01 
    // parsed:, offset 179, len 2, h: name: i1
    // .  .  
       00 09 
    // parsed:, offset 181, len 2, h: descriptor: I
    // .  .  
       00 0f 
    // parsed:, offset 183, len 2, h: attributes_count: 0000
    // .  .  
       00 00 
// parsed:, offset 185, len 0, h: end fields[0] 
// ========== end-ParseMember:i1, desc: I
// parsed:, offset 185, len 2, h: methods_count: 0002
// .  .  
   00 02 
// ========== start-ParseMember:<init>, offset 187, len:96,desc: ()V
// parsed:, offset 187, len 0, h:  methods[0]: 
    // parsed:, offset 187, len 2, h: access_flags: public
    // .  .  
       00 01 
    // parsed:, offset 189, len 2, h: name: <init>
    // .  .  
       00 05 
    // parsed:, offset 191, len 2, h: descriptor: ()V
    // .  .  
       00 0c 
    // parsed:, offset 193, len 2, h: attributes_count: 0001
    // .  .  
       00 01 
    // parsed:, offset 195, len 0, h:  attributes[0]: 
        // parsed:, offset 195, len 2, h: name: Code
        // .  .  
           00 0a 
        // parsed:, offset 197, len 4, h: length: 00000011
        // .  .  .  .  
           00 00 00 11 
        // parsed:, offset 201, len 2, h: max_stack: 0001
        // .  .  
           00 01 
        // parsed:, offset 203, len 2, h: max_locals: 0001
        // .  .  
           00 01 
        // parsed:, offset 205, len 4, h: code_length: 00000005
        // .  .  .  .  
           00 00 00 05 
        // parsed:, offset 0, len 1, h: 0000: aload_0 // 00
        // *  
           2a 
        // parsed:, offset 1, len 3, h: 0001: invokespecial method{java.lang.Object.<init>:()V}
        // .  .  .  
           b7 00 01 
        // parsed:, offset 4, len 1, h: 0004: return
        // .  
           b1 
        // parsed:, offset 214, len 2, h: exception_table_length: 0000
        // .  .  
           00 00 
        // parsed:, offset 216, len 2, h: attributes_count: 0000
        // .  .  
           00 00 
    // parsed:, offset 218, len 0, h: end attributes[0] 
// parsed:, offset 218, len 0, h: end methods[0] 
// ========== end-ParseMember:<init>, desc: ()V
// ========== start-ParseMember:run, offset 218, len:65,desc: ()Z
// parsed:, offset 218, len 0, h:  methods[1]: 
    // parsed:, offset 218, len 2, h: access_flags: public
    // .  .  
       00 01 
    // parsed:, offset 220, len 2, h: name: run
    // .  .  
       00 06 
    // parsed:, offset 222, len 2, h: descriptor: ()Z
    // .  .  
       00 0b 
    // parsed:, offset 224, len 2, h: attributes_count: 0001
    // .  .  
       00 01 
    // parsed:, offset 226, len 0, h:  attributes[0]: 
        // parsed:, offset 226, len 2, h: name: Code
        // .  .  
           00 0a 
        // parsed:, offset 228, len 4, h: length: 00000029
        // .  .  .  )  
           00 00 00 29 
        // parsed:, offset 232, len 2, h: max_stack: 0002
        // .  .  
           00 02 
        // parsed:, offset 234, len 2, h: max_locals: 0002
        // .  .  
           00 02 
        // parsed:, offset 236, len 4, h: code_length: 0000001d
        // .  .  .  .  
           00 00 00 1d 
        // parsed:, offset 0, len 5, h: 0000: jsr_w 00000013
        // .  .  .  .  .  
//@mod           c9 00 00 00 13 
           c9 00 00 00 ff         
        // parsed:, offset 5, len 1, h: 0005: aload_0 // 00
        // *  
           2a 
        // parsed:, offset 6, len 3, h: 0006: getfield field{dxc.junit.opcodes.jsr_w.jm.T_jsr_w_5.i1:I}
        // .  .  .  
           b4 00 0d 
        // parsed:, offset 9, len 3, h: 0009: sipush #+03e8
        // .  .  .  
           11 03 e8 
        // parsed:, offset 12, len 3, h: 000c: if_icmpne 0011
        // .  .  .  
           a0 00 05 
        // parsed:, offset 15, len 1, h: 000f: iconst_1 // #+01
        // .  
           04 
        // parsed:, offset 16, len 1, h: 0010: ireturn
        // .  
           ac 
        // parsed:, offset 17, len 1, h: 0011: iconst_0 // #+00
        // .  
           03 
        // parsed:, offset 18, len 1, h: 0012: ireturn
        // .  
           ac 
        // parsed:, offset 19, len 1, h: 0013: astore_1 // 01
        // L  
           4c 
        // parsed:, offset 20, len 1, h: 0014: aload_0 // 00
        // *  
           2a 
        // parsed:, offset 21, len 3, h: 0015: sipush #+03e8
        // .  .  .  
           11 03 e8 
        // parsed:, offset 24, len 3, h: 0018: putfield field{dxc.junit.opcodes.jsr_w.jm.T_jsr_w_5.i1:I}
        // .  .  .  
           b5 00 0d 
        // parsed:, offset 27, len 2, h: 001b: ret 01
        // .  .  
           a9 01 
        // parsed:, offset 269, len 2, h: exception_table_length: 0000
        // .  .  
           00 00 
        // parsed:, offset 271, len 2, h: attributes_count: 0000
        // .  .  
           00 00 
    // parsed:, offset 273, len 0, h: end attributes[0] 
// parsed:, offset 273, len 0, h: end methods[1] 
// ========== end-ParseMember:run, desc: ()Z
// parsed:, offset 273, len 2, h: attributes_count: 0001
// .  .  
   00 01 
// parsed:, offset 275, len 0, h:  attributes[0]: 
    // parsed:, offset 275, len 2, h: name: SourceFile
    // .  .  
       00 03 
    // parsed:, offset 277, len 4, h: length: 00000002
    // .  .  .  .  
       00 00 00 02 
    // parsed:, offset 281, len 2, h: source: utf8{"T_jsr_w_5.java"}
    // .  .  
       00 10 
// parsed:, offset 283, len 0, h: end attributes[0] 
// parsed:, offset 283, len 0, h: end classfile
